{"id":"13317354","link":"https://wpdev.uservoice.com/forums/257854-microsoft-edge-developer/suggestions/13317354-please-include-a-bookmark-api-for-the-edge-extensi","title":"Please include a bookmark API for the Edge Extensions","body":"On the extensions API roadmap, the bookmarks (described as \"Used to create, organize, and manipulate bookmarks\") are currently listed as \"Under consideration.\"  I wanted to have a place to explicitly vote for this, as it would be nice to be able to extend the rather broken current system.","votes":"25","user":"https://wpdev.uservoice.com/users/136550793-mark-h","datetime":"2016-04-05","comments":[]}