{"id":"13489659","link":"https://wpdev.uservoice.com/forums/257854-microsoft-edge-developer/suggestions/13489659-an-edge-extension-that-allows-developers-to-create","title":"An Edge Extension that allows developers to create HTTP REST calls","body":"As a SharePoint and web developer, I often have to create and troubleshoot HTTP REST calls.  I would like to manipulate the querystring, headers and body as well as use different HTTP methods (GET, POST, PUT, DELETE, etc.) and see the results.","votes":"29","user":"https://wpdev.uservoice.com/users/160827117-john-palmer","datetime":"2016-04-19","comments":[{"user":"https://wpdev.uservoice.com/users/771466069-anonymous","datetime":"2018-03-28","body":"See also YARC for chrome, Advanced REST client, Postman,  etc. "},{"user":"https://wpdev.uservoice.com/users/714568030-trihydrat","datetime":"2017-11-23","body":"A extension like RESTClient  would be nice!"},{"user":"https://wpdev.uservoice.com/users/358819072-alex-duke","datetime":"2017-04-15","body":"Not exists a Rest Client for Microsoft Edge...."}]}