{"id":"16401487","link":"https://wpdev.uservoice.com/forums/257854-microsoft-edge-developer/suggestions/16401487-edge-extensions-do-not-support-cookies","title":"Edge extensions do not support cookies","body":"Bug: Edge extensions do not support cookies\n<br>Bug was raised by Haibara Ai via stackoverflow","votes":"11","user":"https://wpdev.uservoice.com/users/254700757-daniel-anderton","datetime":"2016-09-28","comments":[{"user":"https://wpdev.uservoice.com/users/795287650-nathar-leichoz","datetime":"2018-06-03","body":"Use \"browser.storage.local.set\" in lieu of cookies."}]}