{"id":"19296619","link":"https://wpdev.uservoice.com/forums/257854-microsoft-edge-developer/suggestions/19296619-implement-overlay-scroll-bar-ms-overflow-style","title":"Implement overlay scroll bar (ms-overflow-style)","body":"When switching between `overflow: scroll` and `overflow: hidden`, the &lt;body&gt; padding changed.\n<br>It is annoying, overlay scroll bar can avoid hack.","votes":"30","user":"https://wpdev.uservoice.com/users/376149913-zcyzcy88","datetime":"2017-05-16","comments":[{"user":"https://wpdev.uservoice.com/users/815793352","datetime":"2018-06-18","body":"<a rel=\"nofollow noreferrer\" href=\"https://www.w3.org/TR/css-overflow-4/#scollbar-gutter-property\">https://www.w3.org/TR/css-overflow-4/#scollbar-gutter-property</a>"},{"user":"https://wpdev.uservoice.com/users/726222271-r0b","datetime":"2017-12-15","body":"<a rel=\"nofollow noreferrer\" href=\"https://www.w3.org/TR/css-overflow-4/#overlay-scrollbars\">https://www.w3.org/TR/css-overflow-4/#overlay-scrollbars</a>"}]}