{"id":"33683863","link":"https://wpdev.uservoice.com/forums/257854-microsoft-edge-developer/suggestions/33683863-rtsp-streaming-protocol-support","title":"RTSP Streaming Protocol Support","body":"The video surveillance industry relies heavily on the RTSP protocol (as implemented by ffmpeg, vlc media player, live555, etc) for streaming h264 and h265 video content.","votes":"26","user":"https://wpdev.uservoice.com/users/768356539-andrew-buchanan","datetime":"2018-03-19","comments":[{"user":"https://wpdev.uservoice.com/users/774104263-googleflights","datetime":"2018-04-05","body":"RTSP is one of the most important piece in the interoperability puzzle. Interoperability on streaming media systems is tough because there are many related components (Players, Servers, Encoders/Tools) that you must share common mechanisms. Encoders and content-creation tools must be able to store content in files that servers can read. \n<br><a rel=\"nofollow noreferrer\" href=\"http://google--flights.me\">http://google--flights.me</a>"}]}