{"id":"34150993","link":"https://wpdev.uservoice.com/forums/257854-microsoft-edge-developer/suggestions/34150993-get-rid-of-the-borders","title":"Get rid of the BORDERS","body":"THE NEW UPDATE FOR MICROSOFT EDGE IS RIDICULOUS AS THE PREVIOUS VERSION WOULD LET YOU CLOSE WINDOWS EASY WITH THE SELECT BUTTON ON XBOX ONE:NOW IN THE PROCESS OF SELLING MY XBOX FOR PS4 AS I ONLY GOT XBOX CAUSE I LIKED THE BROWSER WHICH WAS EASY TO NAVIGATE.AND BROWSE UNTILL NOW WITH THE ADDRESS BORDERS\n","votes":"3","user":"https://wpdev.uservoice.com/users/783796390-brett","datetime":"2018-05-03","comments":[]}