{"id":"35328763","link":"https://wpdev.uservoice.com/forums/257854-microsoft-edge-developer/suggestions/35328763-unable-to-undo-code-change-in-the-debugger","title":"Unable to Undo code change in the Debugger.","body":"I made a change to a javascript code in the Debugger and unable to figure out how to undo the change without refreshing the Edge browser.  There should be an undo button (or a re-do button)","votes":"2","user":"https://wpdev.uservoice.com/users/847039864-terry","datetime":"2018-09-05","comments":[]}