{"id":"19248226","link":"https://wpdev.uservoice.com/forums/110705-universal-windows-platform/suggestions/19248226-codecs-for-uwp-media-element","title":"Codecs for UWP Media Element","body":"uwp Media Element or MediaPlayerElement are fantastic with UI.But their codecs to play different kinds of audio and video files is very limited. Please integrate ffmpeg or vlc libraries by default in these xaml elements to make it easier for developers to build apps that run all kinds of video and audio files.\n<br>Thankyou","votes":"19","user":"https://wpdev.uservoice.com/users/104786655","datetime":"2017-05-11","comments":[]}