{"id":"2640081","link":"https://wpdev.uservoice.com/forums/110705-universal-windows-platform/suggestions/2640081-support-udp-broadcast","title":"Support UDP Broadcast","body":"UDP Broadcast (send to 255.255.255.255) is not supported. In this case an exception is thrown.","votes":"15","user":"https://wpdev.uservoice.com/users/21537086-werner-kaa","datetime":"2012-02-29","comments":[{"user":"https://wpdev.uservoice.com/users/36508681-rp-interactive","datetime":"2013-05-22","body":"I may not get the idea behind this, but don't turn Windows Phones into ordinary PCs for no reason, their main function are just to be phones and be damn good at it."}]}