{"id":"32093974","link":"https://wpdev.uservoice.com/forums/110705-universal-windows-platform/suggestions/32093974-automate-updates-for-on-bash-ubuntu-on-windows-10","title":"Automate updates for on Bash Ubuntu on Windows 10","body":"It would be nice to have a way to automate update/upgrade Bash Ubuntu on Windows 10 that does not require to start Bash.\n<br>To clarify, that this can be done from Windows 10 as a part of Windows administration and configuration, for instance via Group Policies, PowerShell, Windows Updates, Schedule Tasks, etc.","votes":"1","user":"https://wpdev.uservoice.com/users/703133059-ernestogit","datetime":"2017-11-01","comments":[{"user":"https://wpdev.uservoice.com/users/695281537-wsluser","datetime":"2018-06-18","body":"@ernestogIT You can create a task in Task scheduler to do this. See the Uservoice \"Support background tasks\" under the commandline Uservoice forum."}]}