{"id":"33268000","link":"https://wpdev.uservoice.com/forums/110705-universal-windows-platform/suggestions/33268000-calcbinding-for-uwp","title":"CalcBinding for UWP","body":"CalcBinding is an advanced Binding markup extension that allows you to write calculated binding expressions in XAML, without custom converters. CalcBinding can automatically perform bool to visibility conversion, inverse your expression and more. CalcBinding makes binding expressions shorter and more user-friendly.","votes":"22","user":"https://wpdev.uservoice.com/users/352036801-vijay-nirmal","datetime":"2018-02-09","comments":[]}