{"id":"33476653","link":"https://wpdev.uservoice.com/forums/110705-universal-windows-platform/suggestions/33476653-closing-streamsocket-should-stop-all-pending-async","title":"Closing StreamSocket should stop all pending asynchronous operations","body":"Closing the StreamSocket (by disposing/deleting it) should stop all the pending asynchronous operations, reads or writes. It used to do this in Windows 8 and early Windows 10 versions but this apparently changed a while ago.","votes":"1","user":"https://wpdev.uservoice.com/users/761255011-benoit-foucher","datetime":"2018-02-28","comments":[]}