{"id":"34519024","link":"https://wpdev.uservoice.com/forums/110705-universal-windows-platform/suggestions/34519024-fix-bug-where-dns-sd-does-not-unregister-service","title":"Fix bug where DNS-SD does not unregister service","body":"There seems to be a bug in DNS-SD where finished services are not actually getting unregistered. So they get stuck in all the networks' devices' cache and never go away.","votes":"5","user":"https://wpdev.uservoice.com/users/805672132-e-wing","datetime":"2018-06-11","comments":[{"user":"https://wpdev.uservoice.com/users/875938939-chris-ross","datetime":"2019-01-22","body":"Has there been any progress on this?  At the moment this is a real issue to using the API."}]}