{"id":"36523795","link":"https://wpdev.uservoice.com/forums/110705-universal-windows-platform/suggestions/36523795--bug-broker-infrastructure-doesn-t-respect-alway","title":"[Bug] Broker Infrastructure doesn't respect \"Always Allow in background\"","body":"Applications configured for \"Always allow in background\" do not in fact receive reliable invocation of SocketBroker \"KeepAliveTimerExpired\" or TimeTrigger events, making the development of dependable always-connected UWP applications not possible. ","votes":"1","user":"https://wpdev.uservoice.com/users/251674894-simon-bond","datetime":"2019-01-14","comments":[]}