{"id":"9636918","link":"https://wpdev.uservoice.com/forums/110705-universal-windows-platform/suggestions/9636918-custom-windows-media-audio-audiograph-nodes","title":"Custom Windows.Media.Audio.AudioGraph nodes","body":"Please provide a way to implement AudioGraph nodes for custom Media Foundation MediaSource (input nodes) and MediaSinks (output nodes).\n<br>It could be something like:\n<br>for input nodes\n<br>IAsyncOperation&lt;CreateAudioCustomInputNodeResult&gt; AudioGraph.CreateCustomInputNodeAsync(IMediaExtension customMediaSurce);\n<br>IAsyncOperation&lt;CreateAudioCustomInputNodeResult&gt; AudioGraph.CreateCustomInputNodeAsync(AudioEncodingProperties encodingProperties, IMediaExtension customMediaSurce);\n<br>IAsyncOperation&lt;CreateAudioCustomInputNodeResult&gt; AudioGraph.CreateCustomInputNodeAsync(String customMediaSourceActivationId, IPropertySet customMediaSourceSettings)\n<br>IAsyncOperation&lt;CreateAudioCustomInputNodeResult&gt; AudioGraph.CreateCustomInputNodeAsync(AudioEncodingProperties encodingProperties, String customMediaSourceActivationId, IPropertySet customMediaSourceSettings);","votes":"13","user":"https://wpdev.uservoice.com/users/51505439-lorenzrox","datetime":"2015-09-05","comments":[]}