{"id":"15597342","link":"https://wpdev.uservoice.com/forums/266908-command-prompt-console-windows-subsystem-for-l/suggestions/15597342-keyboard-remapping-should-be-supported","title":"Keyboard Remapping Should Be Supported","body":"GNU APL builds and installs flawlessly under Ubuntu on Windows, but it is necessary to remap the keyboard in order to enter input in the APL character set.  apt-get installs \"setxkbmap\" fine, but when you try to run it, you get \"Error loading new keyboard description.\"","votes":"11","user":"https://wpdev.uservoice.com/users/213021126-mike-duvos","datetime":"2016-08-08","comments":[]}