{"id":"17612383","link":"https://wpdev.uservoice.com/forums/266908-command-prompt-console-windows-subsystem-for-l/suggestions/17612383-stdio-for-windows-gui-apps","title":"stdio for Windows GUI apps","body":"Add support for windows GUI apps to write to stdout/stderr and read from stdin.\n<br>I see this as a link time option and an additional flag set in the binary executable.","votes":"7","user":"https://wpdev.uservoice.com/users/303124513-mozgiii","datetime":"2017-01-03","comments":[{"user":"https://wpdev.uservoice.com/users/58070608-erkin-alp-g%C3%BCney","datetime":"2017-02-19","body":"It is possible, however causes an extra CLI window to open."}]}