{"id":"37902202","link":"https://wpdev.uservoice.com/forums/266908-command-prompt-console-windows-subsystem-for-l/suggestions/37902202-wsl2-ability-to-choose-network-adapter-setting","title":"WSL2: Ability to choose network adapter setting","body":"The title pretty much says it all. Right now it seems to be running with as a host-only network, which works really well in most use cases, however it would be nice to have the possibility of choosing something else.","votes":"2","user":"https://wpdev.uservoice.com/users/907029931","datetime":"2019-06-13","comments":[]}